macos_ui_automation/__init__.py
macos_ui_automation/bridges/__init__.py
macos_ui_automation/bridges/factory.py
macos_ui_automation/bridges/fake_bridge.py
macos_ui_automation/bridges/interfaces.py
macos_ui_automation/bridges/real_bridge.py
macos_ui_automation/bridges/types.py
macos_ui_automation/core/__init__.py
macos_ui_automation/core/actions.py
macos_ui_automation/core/elements.py
macos_ui_automation/core/registry.py
macos_ui_automation/core/state.py
macos_ui_automation/interfaces/__init__.py
macos_ui_automation/interfaces/cli.py
macos_ui_automation/interfaces/mcp_server.py
macos_ui_automation/models/__init__.py
macos_ui_automation/models/types.py
macos_ui_automation/selectors/__init__.py
macos_ui_automation/selectors/jsonpath.py
macos_ui_automation_mcp-0.2.0.dist-info/METADATA
macos_ui_automation_mcp-0.2.0.dist-info/WHEEL
macos_ui_automation_mcp-0.2.0.dist-info/entry_points.txt
macos_ui_automation_mcp-0.2.0.dist-info/RECORD
