Metadata-Version: 2.4
Name: macos-ui-automation-mcp
Version: 0.2.0
Summary: MCP server for macOS UI automation with Claude Desktop/Code integration, plus Python library and CLI interfaces
Project-URL: Homepage, https://github.com/mb-dev/macos-ui-automation-mcp
Project-URL: Repository, https://github.com/mb-dev/macos-ui-automation-mcp.git
Project-URL: Issues, https://github.com/mb-dev/macos-ui-automation-mcp/issues
Project-URL: Documentation, https://github.com/mb-dev/macos-ui-automation-mcp#readme
Author: mochen
Keywords: accessibility,automation,claude,jsonpath,macos,mcp,ui
Classifier: Development Status :: 4 - Beta
Classifier: Environment :: MacOS X
Classifier: Intended Audience :: Developers
Classifier: License :: OSI Approved :: MIT License
Classifier: Operating System :: MacOS
Classifier: Programming Language :: Python :: 3
Classifier: Programming Language :: Python :: 3.10
Classifier: Programming Language :: Python :: 3.11
Classifier: Programming Language :: Python :: 3.12
Classifier: Programming Language :: Python :: 3.13
Classifier: Topic :: Desktop Environment :: Window Managers
Classifier: Topic :: Scientific/Engineering :: Human Machine Interfaces
Classifier: Topic :: Software Development :: Libraries :: Python Modules
Classifier: Topic :: System :: Systems Administration
Requires-Python: >=3.10
Requires-Dist: mcp[cli]>=1.0.0
Requires-Dist: pydantic>=2.10.0
Requires-Dist: pyobjc-core>=10.0
Requires-Dist: pyobjc-framework-applicationservices>=10.0
Requires-Dist: pyobjc-framework-cocoa>=10.0
Requires-Dist: python-jsonpath>=1.0.0
Requires-Dist: typing-extensions>=4.0.0
